[{
  "type": "project",
  "config": {
    "buildName": "Ace Commit",
    "branchName": "master"
  },
  "caption": "Ace Commit",
  "columnSpan": 2,
  "rowSpan": 2
}, {
  "type": "message",
  "config": {
    "messageKey": "sprintTheme",
    "classes": ["fancy"]
  },
  "caption": "Current Theme",
  "columnSpan": 2,
  "rowSpan": 1
}, {
  "type": "clock",
  "config": {
    "timezone": "Europe/London"
  },
  "caption": "UK Time",
  "columnSpan": 1,
  "rowSpan": 1
}, {
  "type": "project",
  "config": {
    "buildName": "Ngyn Commit",
    "branchName": "master"
  },
  "caption": "Ngyn Commit",
  "columnSpan": 1,
  "rowSpan": 1
}, {
  "type": "project",
  "config": {
    "buildName": "Vcdb Commit",
    "branchName": "master"
  },
  "caption": "Vcdb Commit",
  "columnSpan": 1,
  "rowSpan": 1
}, {
  "type": "project",
  "config": {
    "buildName": "Installer Commit",
    "branchName": "master"
  },
  "caption": "Installer Commit",
  "columnSpan": 1,
  "rowSpan": 1
}, {
  "type": "project",
  "config": {
    "buildName": "Grid Commit",
    "branchName": "master"
  },
  "caption": "Grid Commit",
  "columnSpan": 1,
  "rowSpan": 1
}, {
  "type": "project",
  "config": {
    "buildName": "Base Commit",
    "branchName": "master"
  },
  "caption": "Base Commit",
  "columnSpan": 1,
  "rowSpan": 1
}, {
  "type": "project",
  "config": {
    "buildName": "Ace Commit",
    "branchName": "prff"
  },
  "caption": "Ace PRFF",
  "columnSpan": 1,
  "rowSpan": 1
}, {
  "type": "project",
  "config": {
    "buildName": "Ace Daily Deploy (PRFF)",
    "branchName": "prff"
  },
  "caption": "Ace PRFF Deploy",
  "columnSpan": 1,
  "rowSpan": 1
}, {
  "type": "project",
  "config": {
    "buildName": "Ace Daily Deploy (MVFF)",
    "branchName": "mvff"
  },
  "caption": "Ace MVFF Deploy",
  "columnSpan": 1,
  "rowSpan": 1
}, {
  "type": "project",
  "config": {
    "buildName": "Ace Daily Deploy",
    "branchName": "master"
  },
  "caption": "Ace Daily",
  "columnSpan": 1,
  "rowSpan": 1
}, {
  "type": "project",
  "config": {
    "buildName": "Ace End To End Test",
    "branchName": "master"
  },
  "caption": "Ace End To End",
  "columnSpan": 1,
  "rowSpan": 1
}, {
  "type": "project",
  "config": {
    "buildName": "Ace Daily Upgrade",
    "branchName": "master"
  },
  "caption": "Ace Upgrade",
  "columnSpan": 1,
  "rowSpan": 1
}]